README.md
setup.py
locuspocus/__init__.py
locuspocus/chromosome.py
locuspocus/exceptions.py
locuspocus/fasta.py
locuspocus/loci.py
locuspocus/locus.py
locuspocus/locusattrs.py
locuspocus/locusview.py
locuspocus/ontology.py
locuspocus/subloci.py
locuspocus/term.py
locuspocus.egg-info/PKG-INFO
locuspocus.egg-info/SOURCES.txt
locuspocus.egg-info/dependency_links.txt
locuspocus.egg-info/requires.txt
locuspocus.egg-info/top_level.txt